easy_serverless/__init__.py
easy_serverless/aws/__init__.py
easy_serverless/aws/easy_api.py
easy_serverless/aws/easy_lambda.py
easy_serverless/aws/errors.py
easy_serverless/aws/helpers.py
easy_serverless-1.0.1.dist-info/METADATA
easy_serverless-1.0.1.dist-info/WHEEL
easy_serverless-1.0.1.dist-info/top_level.txt
easy_serverless-1.0.1.dist-info/RECORD
